{
  "sections": {
    "banner": {
      "type": "main-collection-banner",
      "settings": {
        "show_collection_image": false,
        "focal_point": "center_top",
        "overlay_opacity": 40,
        "overlay_color": "#000000",
        "text_color": "#454236",
        "show_border": true,
        "show_heading": true,
        "show_small_heading": true,
        "show_description": true,
        "heading_alignment": "left",
        "text_max_width": 38
      }
    },
    "product-grid": {
      "type": "main-collection-product-grid",
      "settings": {
        "show_sort": false,
        "show_filters": false,
        "show_filter_swatches": false,
        "show_filter_chips": false,
        "filter_style": "sidebar",
        "collapse_filter_groups": false,
        "show_swatches": false,
        "products_per_row": 4,
        "products_per_row_mobile": 2,
        "aspect_ratio": "square",
        "per_page": 12,
        "pagination": "paginated"
      }
    }
  },
  "order": [
    "banner",
    "product-grid"
  ]
}
